gkdbutils/__init__.py
gkdbutils/__version__.py
gkdbutils/ingesters/__init__.py
gkdbutils/ingesters/cassandra/__init__.py
gkdbutils/ingesters/cassandra/ingestGenericDatabaseTable.py
gkdbutils/ingesters/mysql/__init__.py
gkdbutils/ingesters/mysql/ingestGenericDatabaseTable.py
gkdbutils-0.0.4.dist-info/LICENSE
gkdbutils-0.0.4.dist-info/METADATA
gkdbutils-0.0.4.dist-info/WHEEL
gkdbutils-0.0.4.dist-info/entry_points.txt
gkdbutils-0.0.4.dist-info/top_level.txt
gkdbutils-0.0.4.dist-info/RECORD
