Metadata-Version: 2.1
Name: gkdbutils
Version: 0.0.4
Summary: A collection useful utilities - mostly related to astronomy
Home-page: https://github.com/genghisken/gkdbutils
Author: genghisken
Author-email: ken.w.smith@gmail.com
License: MIT
Platform: UNKNOWN
Classifier: Development Status :: 4 - Beta
Classifier: License :: OSI Approved :: MIT License
Classifier: Programming Language :: Python :: 3.6
Classifier: Topic :: Utilities
Requires-Python: >=3.6
